LICENSE
MANIFEST.in
README.md
setup.py
helpme/__init__.py
helpme/defaults.py
helpme/helpme.cfg
helpme/version.py
helpme.egg-info/PKG-INFO
helpme.egg-info/SOURCES.txt
helpme.egg-info/dependency_links.txt
helpme.egg-info/entry_points.txt
helpme.egg-info/not-zip-safe
helpme.egg-info/requires.txt
helpme.egg-info/top_level.txt
helpme/action/__init__.py
helpme/action/record.py
helpme/action/submit.py
helpme/client/__init__.py
helpme/client/config.py
helpme/client/help.py
helpme/client/list.py
helpme/logger/__init__.py
helpme/logger/message.py
helpme/logger/namer.py
helpme/logger/progress.py
helpme/logger/spinner.py
helpme/main/README.md
helpme/main/__init__.py
helpme/main/base/__init__.py
helpme/main/base/auth.py
helpme/main/base/headers.py
helpme/main/base/http.py
helpme/main/base/settings.py
helpme/main/discourse/__init__.py
helpme/main/discourse/utils.py
helpme/main/github/__init__.py
helpme/main/github/utils.py
helpme/main/uservoice/__init__.py
helpme/main/workers/__init__.py
helpme/main/workers/tasks.py
helpme/main/workers/worker.py
helpme/utils/__init__.py
helpme/utils/fileio.py
helpme/utils/format.py
helpme/utils/memory.py
helpme/utils/metrics.py
helpme/utils/settings.py
helpme/utils/terminal.py