Metadata-Version: 2.1
Name: helpme
Version: 0.0.41
Summary: command line client for helping you out.
Home-page: http://www.github.com/researchapps/helpme-client
Author: Vanessa Sochat
Author-email: vsochat@stanford.edu
Maintainer: Vanessa Sochat
Maintainer-email: vsochat@stanford.edu
License: LICENSE
Keywords: hpc,help,asciinema,questions,answers,client
Platform: UNKNOWN
Classifier: Intended Audience :: Science/Research
Classifier: Intended Audience :: Developers
Classifier: License :: OSI Approved :: Mozilla Public License 2.0 (MPL 2.0)
Classifier: Programming Language :: C
Classifier: Programming Language :: Python
Classifier: Topic :: Software Development
Classifier: Topic :: Scientific/Engineering
Classifier: Operating System :: Unix
Classifier: Programming Language :: Python :: 3
Provides-Extra: all
Provides-Extra: asciinema
Provides-Extra: uservoice
Provides-Extra: discourse
Provides-Extra: github
